PyMessagingFramework/__init__.py
PyMessagingFramework/consumers.py
PyMessagingFramework/framework.py
PyMessagingFramework/utils.py
pymessagingframework-2.0.1.dist-info/LICENSE
pymessagingframework-2.0.1.dist-info/WHEEL
pymessagingframework-2.0.1.dist-info/METADATA
pymessagingframework-2.0.1.dist-info/RECORD
