Metadata-Version: 2.1
Name: pymessagingframework
Version: 2.0.1
Summary: Messaging infrastructure for communication between microservices in Python
License: MIT
Keywords: messaging,rabbitmq,infrastructure,microservice
Author: zuhairmhtb
Author-email: zuhairmhtb@gmail.com
Requires-Python: >=3.4
Classifier: License :: OSI Approved :: MIT License
Classifier: Operating System :: OS Independent
Classifier: Programming Language :: Python :: 3
Classifier: Programming Language :: Python :: 3.10
Classifier: Programming Language :: Python :: 3.4
Classifier: Programming Language :: Python :: 3.5
Classifier: Programming Language :: Python :: 3.6
Classifier: Programming Language :: Python :: 3.7
Classifier: Programming Language :: Python :: 3.8
Classifier: Programming Language :: Python :: 3.9
Requires-Dist: pika (==1.3.0)
